bayesdb/__init__.py
bayesdb/api_utils.py
bayesdb/bql.py
bayesdb/bql_grammar.py
bayesdb/client.py
bayesdb/client_remote.py
bayesdb/data_utils.py
bayesdb/diagnostics_utils.py
bayesdb/engine.py
bayesdb/estimate_columns_utils.py
bayesdb/functions.py
bayesdb/jsonrpc_server.py
bayesdb/pairwise.py
bayesdb/parser.py
bayesdb/persistence_layer.py
bayesdb/plotting_utils.py
bayesdb/pyparser.py
bayesdb/select_utils.py
bayesdb/server_remote.py
bayesdb/settings.py
bayesdb/starcluster_plugin.py
bayesdb/tester.py
bayesdb/utils.py
bayesdb/tests/__init__.py
bayesdb/tests/test_client.py
bayesdb/tests/test_cyclic.py
bayesdb/tests/test_demos.py
bayesdb/tests/test_engine.py
bayesdb/tests/test_parser.py
bayesdb/tests/test_utils.py
BayesDB-0.2.0.dist-info/DESCRIPTION.rst
BayesDB-0.2.0.dist-info/entry_points.txt
BayesDB-0.2.0.dist-info/METADATA
BayesDB-0.2.0.dist-info/metadata.json
BayesDB-0.2.0.dist-info/RECORD
BayesDB-0.2.0.dist-info/top_level.txt
BayesDB-0.2.0.dist-info/WHEEL
