Metadata-Version: 2.0
Name: BayesDB
Version: 0.2.0
Summary: UNKNOWN
Home-page: probcomp.csail.mit.edu/bayesdb
Author: MIT Probabilistic Computing Project
Author-email: bayesdb@mit.edu
License: Apache License, Version 2.0
Platform: UNKNOWN
Requires-Dist: jsonrpc
Requires-Dist: requests
Requires-Dist: Twisted
Requires-Dist: pyOpenSSL
Requires-Dist: numpy
Requires-Dist: scipy
Requires-Dist: matplotlib (>=1.2.0)
Requires-Dist: Sphinx
Requires-Dist: pytest
Requires-Dist: prettytable
Requires-Dist: cmd2
Requires-Dist: pyparsing (>=2.0.1)
Requires-Dist: ipython
Requires-Dist: pandas (>=0.13)
